postboy
