Metadata-Version: 1.1
Name: postboy
Version: 0.3.4
Summary: simple distributed emailing system.
Home-page: http://github.com/mosquito/postboy
Author: Dmitry Orlov <me@mosquito.su>
Author-email: me@mosquito.su
License: MIT
Platform: all
Classifier: Environment :: Console
Classifier: Programming Language :: Python
Requires: pika
